super_simplex/__init__.py
super_simplex/const.py
super_simplex/functions.py
super_simplex/generator.py
super_simplex/l_math.py
super_simplex/l_random.py
super_simplex/dimensions/__init__.py
super_simplex/dimensions/four.py
super_simplex/dimensions/three.py
super_simplex/dimensions/two.py
super_simplex-1.0.1.dist-info/METADATA
super_simplex-1.0.1.dist-info/WHEEL
super_simplex-1.0.1.dist-info/top_level.txt
super_simplex-1.0.1.dist-info/RECORD
