Metadata-Version: 2.4
Name: super_simplex
Version: 1.0.1
Summary: Super Simplex Noise for Python
Author: Sylvie Isla
Author-email: sylvieisla.std@gmail.com
Keywords: open_simplex_2s open_simplex2s opensimplex2s open_simplex opensimplex super_simplex supersimplex simplex noise gradient_noise coherent_noise
Classifier: Programming Language :: Python :: 3
Classifier: Development Status :: 2 - Pre-Alpha
Classifier: Intended Audience :: Developers
Classifier: Topic :: Scientific/Engineering :: Mathematics
Classifier: License :: CC0 1.0 Universal (CC0 1.0) Public Domain Dedication
Classifier: Operating System :: OS Independent
Requires-Python: >=3.6
Requires-Dist: numpy>=1.22
Dynamic: author
Dynamic: author-email
Dynamic: classifier
Dynamic: description
Dynamic: description-content-type
Dynamic: keywords
Dynamic: requires-dist
Dynamic: requires-python
Dynamic: summary
